radondp/__init__.py
radondp/balancers.py
radondp/classifiers.py
radondp/cli.py
radondp/hyper_parameters.py
radondp/model_validation.py
radondp/normalizers.py
radondp/predictors.py
radon_defect_predictor-0.2.7.dist-info/LICENSE
radon_defect_predictor-0.2.7.dist-info/METADATA
radon_defect_predictor-0.2.7.dist-info/WHEEL
radon_defect_predictor-0.2.7.dist-info/entry_points.txt
radon_defect_predictor-0.2.7.dist-info/top_level.txt
radon_defect_predictor-0.2.7.dist-info/RECORD
