Metadata-Version: 2.1
Name: radon-defect-predictor
Version: 0.2.7
Summary: A Python library to train machine learning models for defect prediction of infrastructure code.
Home-page: https://github.com/radon-h2020/radon-defect-predictor
Author: Stefano Dalla Palma
Author-email: stefano.dallapalma0@gmail.com
Maintainer: Stefano Dalla Palma
License: UNKNOWN
Download-URL: https://github.com/radon-h2020/radon-defect-predictor/archive/0.2.7.tar.gz
Platform: UNKNOWN
Classifier: Development Status :: 4 - Beta
Classifier: Intended Audience :: Developers
Classifier: Programming Language :: Python :: 3.6
Classifier: Programming Language :: Python :: 3.7
Classifier: Programming Language :: Python :: 3.8
Classifier: Programming Language :: Python :: 3.9
Classifier: License :: OSI Approved :: Apache Software License
Classifier: Topic :: Software Development :: Libraries :: Python Modules
Classifier: Operating System :: OS Independent
Requires-Python: >=3.6
Requires-Dist: ansiblemetrics (~=0.3.7)
Requires-Dist: imbalanced-learn (~=0.7.0)
Requires-Dist: joblib (~=0.17.0)
Requires-Dist: jsonpickle (~=1.4.1)
Requires-Dist: numpy (~=1.19.4)
Requires-Dist: pandas (~=1.1.4)
Requires-Dist: repository-scorer (~=0.2.1)
Requires-Dist: requests (~=2.24.0)
Requires-Dist: scikit-learn (~=0.24.1)
Requires-Dist: tosca-metrics (~=0.0.6)
